idz/__init__.py
idz/__main__.py
idz/main1.py
idz/main2.py
idz-0.1.0.dist-info/WHEEL
idz-0.1.0.dist-info/METADATA
idz-0.1.0.dist-info/RECORD
